data_utils/__init__.py
data_utils/dataloaders.py
data_utils/user_data.py
examples/test_curvenet.py
examples/test_dcp.py
examples/test_deepgmr.py
examples/test_masknet.py
examples/test_masknet2.py
examples/test_pcn.py
examples/test_pcrnet.py
examples/test_pnlk.py
examples/test_pointconv.py
examples/test_pointnet.py
examples/test_prnet.py
examples/test_rpmnet.py
examples/train_PointNetLK.py
examples/train_dcp.py
examples/train_deepgmr.py
examples/train_masknet.py
examples/train_pcn.py
examples/train_pcrnet.py
examples/train_pointconv.py
examples/train_pointnet.py
examples/train_prnet.py
examples/train_rpmnet.py
losses/__init__.py
losses/chamfer_distance.py
losses/classification.py
losses/correspondence_loss.py
losses/emd.py
losses/frobenius_norm.py
losses/rmse_features.py
models/__init__.py
models/classifier.py
models/curvenet.py
models/dcp.py
models/deepgmr.py
models/dgcnn.py
models/masknet.py
models/masknet2.py
models/pcn.py
models/pcrnet.py
models/pointconv.py
models/pointnet.py
models/pointnetlk.py
models/pooling.py
models/ppfnet.py
models/prnet.py
models/rpmnet.py
models/segmentation.py
ops/__init__.py
ops/data_utils.py
ops/invmat.py
ops/quaternion.py
ops/se3.py
ops/sinc.py
ops/so3.py
ops/transform_functions.py
utils/__init__.py
utils/curvenet_util.py
utils/model_common_utils.py
utils/pointconv_util.py
utils/ppfnet_util.py
utils/svd.py
utils/transformer.py
learning3d-0.2.2.dist-info/LICENSE
learning3d-0.2.2.dist-info/METADATA
learning3d-0.2.2.dist-info/WHEEL
learning3d-0.2.2.dist-info/top_level.txt
learning3d-0.2.2.dist-info/RECORD
