Metadata-Version: 2.1
Name: learning3d
Version: 0.2.2
Summary: Learning3D: A Modern Library for Deep Learning on 3D Point Clouds Data
Author-email: Vinit Sarode <vinitsarode5@gmail.com>
Maintainer-email: Vinit Sarode <vinitsarode5@gmail.com>
License: The MIT License
Project-URL: Homepage, https://github.com/vinits5/learning3d
Project-URL: Repository, https://github.com/vinits5/learning3d
Project-URL: Issues, https://github.com/vinits5/learning3d/issues
Project-URL: Changelog, https://github.com/vinits5/learning3d/CHANGELOG.md
Keywords: Point Clouds,Deep Learning,3D Vision,Point Cloud Registration,Point Cloud Classification,Point Cloud Segmentation
Classifier: Programming Language :: Python :: 3
Classifier: License :: OSI Approved :: MIT License
Classifier: Operating System :: OS Independent
Requires-Python: >=3.8
License-File: LICENSE
Requires-Dist: torch ==2.0.1
Requires-Dist: torchvision ==0.15.2
Requires-Dist: h5py ==3.8.0
Requires-Dist: ninja ==1.11.1
Requires-Dist: open3d ==0.17.0
Requires-Dist: tensorboardX ==2.6
Requires-Dist: tqdm ==4.65.0
Requires-Dist: scikit-learn ==1.2.2
Requires-Dist: scipy ==1.10.1
Requires-Dist: numpy ==1.24.3
Requires-Dist: transforms3d ==0.4.1
